{"cameraMode":{"drawMode":0,"name":"Shaded","section":"Shading Mode"},"sceneLighting":true,"audioPlay":false,"sceneViewState":{"showFog":true,"showMaterialUpdate":false,"showSkybox":true,"showFlares":true,"showImageEffects":true,"showParticleSystems":true},"in2DMode":false,"pivot":{"x":215.57322692871095,"y":3.5582327842712404,"z":-128.6892852783203},"rotation":{"x":-0.13718043267726899,"y":0.6884703040122986,"z":-0.13521189987659455,"w":-0.6993333101272583},"size":1.9196803569793702,"orthographic":false}